shabdamegha/__init__.py
shabdamegha/shabdamegha.py
tests/__init__.py
tests/test_shabdamegha.py
shabdamegha-0.1.7.dist-info/LICENSE
shabdamegha-0.1.7.dist-info/METADATA
shabdamegha-0.1.7.dist-info/WHEEL
shabdamegha-0.1.7.dist-info/top_level.txt
shabdamegha-0.1.7.dist-info/RECORD
