Metadata-Version: 2.1
Name: shabdamegha
Version: 0.1.7
Summary: A python library to generate word cloud for Odia language with proper rendering of Ligatures (Yuktakshars). ଯୁକ୍ତାକ୍ଷର ଗୁଡ଼ିକୁ ସଠିକ୍‌ ପ୍ରଦର୍ଶିତ କରି ଶବ୍ଦମେଘ ସୃଷ୍ଟି କରିବା ନିମନ୍ତେ ଏକ ପାଇଥନ୍‌ ଲାଇବ୍ରେରୀ
Home-page: https://sbissoyi.github.io/shabdamegha/docs
Author: Dr. Swarupananda Bissoyi
Author-email: swarupananda@gmail.com
Project-URL: Documentation, https://sbissoyi.github.io/shabdamegha/docs
Project-URL: Source, https://github.com/sbissoyi/shabdamegha/
Classifier: Programming Language :: Python :: 3
Classifier: License :: OSI Approved :: MIT License
Classifier: Operating System :: OS Independent
Requires-Python: >=3.7
License-File: LICENSE
Requires-Dist: Pillow
Requires-Dist: uharfbuzz
Requires-Dist: freetype-py
Requires-Dist: numpy
